Metadata-Version: 2.1
Name: devstats
Version: 0.1
Summary: Developer tool for scientific Python libraries
Maintainer-email: Scientific Python <devstats@discuss.scientific-python.org>
License: BSD 3-Clause License
Project-URL: homepage, https://github.com/scientific-python/devstats
Classifier: Development Status :: 3 - Alpha
Classifier: Programming Language :: Python
Requires-Python: >=3.8
License-File: LICENSE
Requires-Dist: click
Requires-Dist: requests
Requires-Dist: jupyter
Requires-Dist: notebook
Requires-Dist: numpy
Requires-Dist: networkx
Provides-Extra: dev
Requires-Dist: changelist ==0.3 ; extra == 'dev'
Provides-Extra: lint
Requires-Dist: pre-commit ==3.4.0 ; extra == 'lint'
